<?xml version="1.0" encoding="utf-8" standalone="yes"?>
<Language Name="Example Language" Author="Pothead" Version="0.698" Revision="1" RightToLeft="0">
	<Strings>
		<String Name="ActiveSearchString">Active / Search String</String>
		<String Name="AutoSearchProperties">Autosearch Properties</String>
		<String Name="AutoExcludeThese">Exclude These Strings (Separate With A |)</String>
		<String Name="AutoExtension">One Of These Extensions (Separate With A |)</String>
		<String Name="AutoMatchThese">Match These Strings (Separate With A |)</String>
		<String Name="Copy">Copy</String>
		<String Name="Close">Close</String>
		<String Name="Enabled">Enabled</String>
		<String Name="FdmBrowseAccel">&amp;Browse...</String>
		<String Name="FdmMenuFile">&amp;File</String>
		<String Name="FdmMenuHelp">&amp;Help</String>
		<String Name="FdmMenuView">&amp;View</String>
		<String Name="FdmMenuWindow">&amp;Window</String>
		<String Name="FdmNotepad">Fdm Notepad</String>
		<String Name="FdmSettings">Fdm Settings</String>
		<String Name="FdmSettingsAutoAway">Auto-away on minimize (and back on restore)</String>
		<String Name="MaxSize">Max size</String>
		<String Name="MinSize">Min size</String>
		<String Name="MenuAutoSearch">Autosearch</String>
		<String Name="MenuFdm">&amp;Fdm</String>
		<String Name="MenuFdmAbout">About Fdm</String>
		<String Name="MenuFdmSettings">Fdm Settings</String>
		<String Name="MenuNotepadFrame">Fdm Notepad</String>
		<String Name="OnlyWhereOp">Only where op</String>
		<String Name="Results">Results</String>
		<String Name="SearchString">Search string</String>
		<String Name="SettingsAppearancePage">Extra Appearance</String>
		<String Name="SettingsAppearanceISpoke">Text you write</String>
		<String Name="SettingsAppearanceMyNickSpoken">Your nick spoken</String>
		<String Name="SettingsAppearanceNotOpSpoke">If speaker is not an op</String>
		<String Name="SettingsAppearanceOpSpoke">If speaker is an op</String>
		<String Name="SettingsAppearanceRequiresRestart">Note; most of these options require that you restart Fdm</String>
		<String Name="SettingsAppearanceTextColouring">Text colouring</String>
		<String Name="SettingsFdmLanguageFile">Fdm Language file</String>
		<String Name="Size">Size</String>
		<String Name="SizeModes">If size is</String>
		<String Name="SizeType">Size is in</String>
		<String Name="SourceType">Type of search</String>
		<String Name="StringFalse">False</String>
		<String Name="StringTrue">True</String>
	</Strings>
</Language>
